<?xml version="1.0" encoding="utf-8"?>
<SoundBanksInfo Platform="Windows" BasePlatform="Windows" SchemaVersion="11" SoundbankVersion="128">
	<RootPaths>
		<ProjectRoot>E:\ParticleCity\ParticleCityWwise\</ProjectRoot>
		<SourceFilesRoot>E:\ParticleCity\ParticleCityWwise\.cache\Windows\</SourceFilesRoot>
		<SoundBanksRoot>E:\ParticleCity\ParticleCityUnity\Assets\StreamingAssets\Audio\GeneratedSoundBanks\Windows\</SoundBanksRoot>
		<ExternalSourcesInputFile></ExternalSourcesInputFile>
		<ExternalSourcesOutputRoot>E:\ParticleCity\ParticleCityWwise\GeneratedSoundBanks\Windows</ExternalSourcesOutputRoot>
	</RootPaths>
	<DialogueEvents/>
	<StreamedFiles/>
	<MediaFilesNotInAnyBank/>
	<SoundBanks>
		<SoundBank Id="1355168291" Language="SFX">
			<ObjectPath>Init</ObjectPath>
			<ShortName>Init</ShortName>
			<Path>Init.bnk</Path>
		</SoundBank>
		<SoundBank Id="1831431028" Language="SFX">
			<ObjectPath>\SoundBanks\Test Work  Unit\TestSoundBank</ObjectPath>
			<ShortName>TestSoundBank</ShortName>
			<Path>TestSoundBank.bnk</Path>
			<IncludedEvents>
				<Event Id="973706497" Name="Play_StoryBGM" ObjectPath="\Events\Test Work Unit\Play_StoryBGM"/>
				<Event Id="2476052365" Name="Play_TweetRevealCommon" ObjectPath="\Events\Default Work Unit\Play_TweetRevealCommon" MaxAttenuation="100.000000"/>
				<Event Id="3160623154" Name="Silent" ObjectPath="\Events\Default Work Unit\Silent" MaxAttenuation="0.000000"/>
			</IncludedEvents>
			<IncludedMemoryFiles>
				<File Id="34834793" Language="SFX">
					<ShortName>Tweet-03 - Twist - e Twist.wav</ShortName>
					<Path>SFX\Tweet-03 - Twist - e Twist_9511B34A.wem</Path>
				</File>
				<File Id="42020522" Language="SFX">
					<ShortName>Tweet-Long_03.wav</ShortName>
					<Path>SFX\Tweet-Long_03_9511B34A.wem</Path>
				</File>
				<File Id="46944213" Language="SFX">
					<ShortName>PCBGM-atmosphere.wav</ShortName>
					<Path>SFX\PCBGM-atmosphere_9511B34A.wem</Path>
				</File>
				<File Id="91450912" Language="SFX">
					<ShortName>Tweet-Short_01.wav</ShortName>
					<Path>SFX\Tweet-Short_01_9511B34A.wem</Path>
				</File>
				<File Id="122761794" Language="SFX">
					<ShortName>Tweet-Short_02.wav</ShortName>
					<Path>SFX\Tweet-Short_02_9511B34A.wem</Path>
				</File>
				<File Id="138061797" Language="SFX">
					<ShortName>Tweet-Med_01.wav</ShortName>
					<Path>SFX\Tweet-Med_01_9511B34A.wem</Path>
				</File>
				<File Id="223810254" Language="SFX">
					<ShortName>blue piano - Copy.wav</ShortName>
					<Path>SFX\blue piano - Copy_9511B34A.wem</Path>
				</File>
				<File Id="325562668" Language="SFX">
					<ShortName>Tweet-02 - First - b Aurora Pluck(Density).wav</ShortName>
					<Path>SFX\Tweet-02 - First - b Aurora Pluck(Density)_9511B34A.wem</Path>
				</File>
				<File Id="376149469" Language="SFX">
					<ShortName>Tweet-Med-Long_01.wav</ShortName>
					<Path>SFX\Tweet-Med-Long_01_9511B34A.wem</Path>
				</File>
				<File Id="383937372" Language="SFX">
					<ShortName>Tweet-03 - Twist - c Evo 2.wav</ShortName>
					<Path>SFX\Tweet-03 - Twist - c Evo 2_9511B34A.wem</Path>
				</File>
				<File Id="408862344" Language="SFX">
					<ShortName>Tweet-Short_03.wav</ShortName>
					<Path>SFX\Tweet-Short_03_9511B34A.wem</Path>
				</File>
				<File Id="420134523" Language="SFX">
					<ShortName>Tweet-Med-Long_02.wav</ShortName>
					<Path>SFX\Tweet-Med-Long_02_9511B34A.wem</Path>
				</File>
				<File Id="438016900" Language="SFX">
					<ShortName>Tweet-01 - Intro - Starting Loop.wav</ShortName>
					<Path>SFX\Tweet-01 - Intro - Starting Loop_9511B34A.wem</Path>
				</File>
				<File Id="483971353" Language="SFX">
					<ShortName>Tweet-Med-Long_03.wav</ShortName>
					<Path>SFX\Tweet-Med-Long_03_9511B34A.wem</Path>
				</File>
				<File Id="600856261" Language="SFX">
					<ShortName>Tweet-Long_02.wav</ShortName>
					<Path>SFX\Tweet-Long_02_9511B34A.wem</Path>
				</File>
				<File Id="633447123" Language="SFX">
					<ShortName>Tweet-03 - Twist - b Evo 1.wav</ShortName>
					<Path>SFX\Tweet-03 - Twist - b Evo 1_9511B34A.wem</Path>
				</File>
				<File Id="694171849" Language="SFX">
					<ShortName>Tweet-Long_01.wav</ShortName>
					<Path>SFX\Tweet-Long_01_9511B34A.wem</Path>
				</File>
				<File Id="802538555" Language="SFX">
					<ShortName>Tweet-03 - Twist - d Evo 3.wav</ShortName>
					<Path>SFX\Tweet-03 - Twist - d Evo 3_9511B34A.wem</Path>
				</File>
				<File Id="831186808" Language="SFX">
					<ShortName>Tweet-02 - First - a Astral Organ.wav</ShortName>
					<Path>SFX\Tweet-02 - First - a Astral Organ_9511B34A.wem</Path>
				</File>
				<File Id="922462996" Language="SFX">
					<ShortName>Tweet-Med_02.wav</ShortName>
					<Path>SFX\Tweet-Med_02_9511B34A.wem</Path>
				</File>
				<File Id="995012014" Language="SFX">
					<ShortName>Tweet-Med_03.wav</ShortName>
					<Path>SFX\Tweet-Med_03_9511B34A.wem</Path>
				</File>
				<File Id="1049042582" Language="SFX">
					<ShortName>Tweet-Med_04.wav</ShortName>
					<Path>SFX\Tweet-Med_04_9511B34A.wem</Path>
				</File>
				<File Id="1066262541" Language="SFX">
					<ShortName>Tweet-03 - Twist - a haunted spaces.wav</ShortName>
					<Path>SFX\Tweet-03 - Twist - a haunted spaces_9511B34A.wem</Path>
				</File>
			</IncludedMemoryFiles>
		</SoundBank>
	</SoundBanks>
</SoundBanksInfo>
